setup.py
KaUtil/Test.py
KaUtil/__init__.py
KaUtil.egg-info/PKG-INFO
KaUtil.egg-info/SOURCES.txt
KaUtil.egg-info/dependency_links.txt
KaUtil.egg-info/requires.txt
KaUtil.egg-info/top_level.txt
KaUtil/Client/__init__.py
KaUtil/Client/base.py
KaUtil/Client/setting.py
KaUtil/Client/utils.py
KaUtil/Excel/__init__.py
KaUtil/Excel/base.py
KaUtil/Parse/__init__.py