Metadata-Version: 1.0
Name: KaUtil
Version: 1.0.1
Summary: kaka util
Home-page: UNKNOWN
Author: kaka zhang
Author-email: zhangjiaying121@163.com
License: MIT Licence
Keywords: pip,pathtool,timetool,magetool,mage
Platform: any
